arduinopythonserialrpc/__init__.py
arduinopythonserialrpc/arduino_python_serial_rpc.py
arduinopythonserialrpc/engine/__init__.py
arduinopythonserialrpc/engine/action_selector.py
arduinopythonserialrpc/engine/protocol_constants.py
arduinopythonserialrpc/engine/protocol_from_arduino.py
arduinopythonserialrpc/engine/protocol_to_arduino.py
arduinopythonserialrpc/engine/usb_handler.py
arduinopythonserialrpc/engine/usb_receiver_agent.py
arduinopythonserialrpc/exception/__init__.py
arduinopythonserialrpc/exception/local_exception.py
arduinopythonserialrpc/exception/remote_exception.py
arduinopythonserialrpc-1.0.0.dist-info/METADATA
arduinopythonserialrpc-1.0.0.dist-info/WHEEL
arduinopythonserialrpc-1.0.0.dist-info/top_level.txt
arduinopythonserialrpc-1.0.0.dist-info/RECORD
