Metadata-Version: 2.1
Name: arduinopythonserialrpc
Version: 1.0.0
Summary: Python side of a serial communication library with Arduino Card
Home-page: https://github.com/Mauxilium/ArduinoPythonSerialRpc
Author: Gabriele Maris
Author-email: gabriele.maris@mauxilium.it
License: Apache2
Platform: UNKNOWN
Classifier: License :: OSI Approved :: Apache Software License
Classifier: Programming Language :: Python :: 3.7
Requires-Dist: pyserial
Requires-Dist: pytest
